pylodata/__init__.py
pylodata/patterns.py
pylodata/wordlist.py
pylodata/data/liusinitic.tsv
pylodata/data/nj-tree.tre
pylodata/data/nj-tree.tre.rooted
pylodata/data/sagart2005.tre
pylodata/data/wichmannmixezoquean-aligned.tsv
pylodata/data/wichmannmixezoquean-correspondences.tsv
pylodata/data/wichmannmixezoquean-patterns.tsv
pylodata/data/wichmannmixezoquean.tsv
pylodata-0.2.0.dist-info/LICENSE
pylodata-0.2.0.dist-info/METADATA
pylodata-0.2.0.dist-info/WHEEL
pylodata-0.2.0.dist-info/top_level.txt
pylodata-0.2.0.dist-info/RECORD
