Metadata-Version: 2.1
Name: pylodata
Version: 0.2.0
Summary: Python Package for Phylogenetic Reconstruction in Linguistics
Home-page: https://github.com/pylogeny/data
Author: Johann-Mattis List and Taraka Rama and Wesley Scivetti
Author-email: mattis_list@eva.mpg.de
License: MIT
Keywords: data
Platform: any
Classifier: Programming Language :: Python
Classifier: Programming Language :: Python :: 3
Classifier: Programming Language :: Python :: 3.5
Classifier: Programming Language :: Python :: 3.6
Classifier: Programming Language :: Python :: 3.7
Classifier: Programming Language :: Python :: 3.8
Classifier: Programming Language :: Python :: 3.9
Requires-Python: >=3.5
License-File: LICENSE
Provides-Extra: dev
Requires-Dist: pep8 ; extra == 'dev'
Requires-Dist: wheel ; extra == 'dev'
Requires-Dist: twine ; extra == 'dev'
Provides-Extra: test
Requires-Dist: pytest (>=4.3) ; extra == 'test'
Requires-Dist: lingpy ; extra == 'test'
Requires-Dist: pytest-cov ; extra == 'test'
Requires-Dist: coverage (>=4.2) ; extra == 'test'
